ouro/__init__.py
ouro/cli.py
ouro/core.py
ouro/helpers.py
ouro/primitives.py
ouro_ci-0.1.0.dist-info/LICENSE
ouro_ci-0.1.0.dist-info/METADATA
ouro_ci-0.1.0.dist-info/WHEEL
ouro_ci-0.1.0.dist-info/top_level.txt
ouro_ci-0.1.0.dist-info/RECORD
