Metadata-Version: 2.1
Name: ouro-ci
Version: 0.1.0
Summary: ouro is a Python-based DSL for generating GitHub Actions workflows.
Author-email: Savannah Ostrowski <savannah@python.org>
License: MIT License
Project-URL: homepage, https://github.com/ouroboros-tools/ouro
Classifier: Programming Language :: Python :: 3
Classifier: License :: OSI Approved :: MIT License
Classifier: Operating System :: OS Independent
Requires-Python: >=3.13
License-File: LICENSE
Requires-Dist: pydantic>=2.10.4
Requires-Dist: pyyaml>=6.0.2
